nnga/__init__.py
nnga/about.py
nnga/crossover_strategy.py
nnga/initialization_strategy.py
nnga/mutation_strategy.py
nnga/nnga.py
nnga/population_parameters.py
faris_lab_train_model-0.0.10.dist-info/LICENSE
faris_lab_train_model-0.0.10.dist-info/METADATA
faris_lab_train_model-0.0.10.dist-info/WHEEL
faris_lab_train_model-0.0.10.dist-info/top_level.txt
faris_lab_train_model-0.0.10.dist-info/RECORD
