Metadata-Version: 2.1
Name: faris-lab-train-model
Version: 0.0.10
Summary: Neural Network Genetic Algorithm library used for deep learning problems
Home-page: https://farislab.com/
Author: FARIS Lab
Author-email: muhammadfarisadiprabowo1@gmail.com
License: MIT
Platform: UNKNOWN
Classifier: Development Status :: 4 - Beta
Classifier: Intended Audience :: Developers
Classifier: Intended Audience :: Education
Classifier: Intended Audience :: Science/Research
Classifier: Intended Audience :: Information Technology
Classifier: Topic :: Scientific/Engineering
Classifier: Topic :: Scientific/Engineering :: Artificial Intelligence
Classifier: Topic :: Scientific/Engineering :: Information Analysis
Classifier: Topic :: Text Processing
Classifier: Topic :: Text Processing :: Linguistic
Classifier: Topic :: Software Development
Classifier: Topic :: Software Development :: Libraries
Classifier: Programming Language :: Python :: 3.6
Classifier: Programming Language :: Python :: 3.7
Classifier: Programming Language :: Python :: 3.8
Requires-Python: >=3.6
License-File: LICENSE
Requires-Dist: numpy
Requires-Dist: neptune-client
